unicode_obfuscate/__init__.py
unicode_obfuscate/data/confusables.json
unicode_obfuscate/data/intentional.json
unicode_obfuscate-0.1.1.dist-info/LICENSE
unicode_obfuscate-0.1.1.dist-info/WHEEL
unicode_obfuscate-0.1.1.dist-info/METADATA
unicode_obfuscate-0.1.1.dist-info/RECORD
