Metadata-Version: 2.1
Name: unicode-obfuscate
Version: 0.1.1
Summary: Replace unicode characters with visually similar ones.
Home-page: https://github.com/lbellomo/unicode_obfuscate
License: GPL-3.0-only
Author: Lucas Bellomo
Author-email: lbellomo@gmail.com
Requires-Python: >=3.7,<4.0
Classifier: License :: OSI Approved :: GNU General Public License v3 (GPLv3)
Classifier: Programming Language :: Python :: 3
Classifier: Programming Language :: Python :: 3.7
Classifier: Programming Language :: Python :: 3.8
Project-URL: Repository, https://github.com/lbellomo/unicode_obfuscate
